benparse/__init__.py
benparse/dump.py
benparse/load.py
benparse/py.typed
benparse/typing.py
benparse-1.0.2.dist-info/COPYING
benparse-1.0.2.dist-info/COPYING.LESSER
benparse-1.0.2.dist-info/METADATA
benparse-1.0.2.dist-info/WHEEL
benparse-1.0.2.dist-info/top_level.txt
benparse-1.0.2.dist-info/RECORD
