Metadata-Version: 2.1
Name: benparse
Version: 1.0.2
Summary: Bencode parser
Home-page: https://gitlab.com/adralioh/benparse
Author: Adralioh
License: UNKNOWN
Project-URL: Documentation, https://adralioh.gitlab.io/benparse
Keywords: bittorrent bencode
Platform: UNKNOWN
Classifier: Programming Language :: Python :: 3
Classifier: License :: OSI Approved :: GNU General Public License v3 (GPLv3)
Classifier: License :: OSI Approved :: GNU Lesser General Public License v3 (LGPLv3)
Classifier: Operating System :: OS Independent
Classifier: Topic :: Software Development :: Libraries
Classifier: Topic :: Communications :: File Sharing
Classifier: Typing :: Typed
Requires-Python: >=3.6
Requires-Dist: typing-extensions ; python_version < "3.8"
